gensyn_client/__init__.py
gensyn_client/api_client.py
gensyn_client/configuration.py
gensyn_client/exceptions.py
gensyn_client/model_utils.py
gensyn_client/rest.py
gensyn_client/api/__init__.py
gensyn_client/api/augmentation_api.py
gensyn_client/api/default_api.py
gensyn_client/apis/__init__.py
gensyn_client/model/__init__.py
gensyn_client/model/random_type.py
gensyn_client/models/__init__.py
gensyn_client-0.0.2.dist-info/METADATA
gensyn_client-0.0.2.dist-info/WHEEL
gensyn_client-0.0.2.dist-info/top_level.txt
gensyn_client-0.0.2.dist-info/RECORD
