Metadata-Version: 2.1
Name: gensyn-client
Version: 0.0.2
Summary: General Synthesis
Home-page: 
Author: General Synthesis
Author-email: info@general-synthesis.com
License: UNKNOWN
Keywords: OpenAPI,OpenAPI-Generator,General Synthesis
Platform: UNKNOWN
Requires-Python: >=3.6
Requires-Dist: urllib3 (>=1.25.3)
Requires-Dist: python-dateutil
